largeaudio2text/__init__.py
largeaudio2text/Model__Speech_Recognition.py
largeaudio2text-0.1.0.dist-info/METADATA
largeaudio2text-0.1.0.dist-info/WHEEL
largeaudio2text-0.1.0.dist-info/RECORD
