Metadata-Version: 2.1
Name: largeaudio2text
Version: 0.1.0
Summary: 
Author: fahadsalamatrandhawa
Author-email: dreamtwister61814@gmail.com
Requires-Python: >=3.12,<4.0
Classifier: Programming Language :: Python :: 3
Classifier: Programming Language :: Python :: 3.12
Requires-Dist: pydub (>=0.25.1,<0.26.0)
